gyllm/__init__.py
gyllm/envs/__init__.py
gyllm/envs/core.py
gyllm/envs/templates.py
gyllm/envs/simple/__init__.py
gyllm/envs/simple/iterated_games.py
gyllm/learn/__init__.py
gyllm-0.0.1.dist-info/METADATA
gyllm-0.0.1.dist-info/WHEEL
gyllm-0.0.1.dist-info/top_level.txt
gyllm-0.0.1.dist-info/RECORD
