Metadata-Version: 2.4
Name: gyllm
Version: 0.0.1
Summary: Add your description here
Requires-Python: >=3.12
Requires-Dist: datasets>=4.0.0
Requires-Dist: jupyter>=1.1.1
Requires-Dist: jupyterlab>=4.4.5
Requires-Dist: mlx>=0.27.1
Requires-Dist: mlx-lm>=0.26.1
Requires-Dist: notebook-intelligence>=2.2.7
Requires-Dist: pytest>=8.4.1
Requires-Dist: torch>=2.7.1
Requires-Dist: transformers>=4.54.0
